{
  "symbol": "AUDCAD=X",
  "history": [
    {
      "timestamp": "2025-04-19T06:40:44.028Z",
      "price": 0.88205,
      "previousClose": 0.88356,
      "dayHigh": 0.88205,
      "dayLow": 0.88205,
      "change": -0.0015100241,
      "changePercent": -0.17090227
    },
    {
      "timestamp": "2025-04-19T06:40:56.457Z",
      "price": 0.88205,
      "previousClose": 0.88356,
      "dayHigh": 0.88205,
      "dayLow": 0.88205,
      "change": -0.0015100241,
      "changePercent": -0.17090227
    },
    {
      "timestamp": "2025-04-19T06:41:10.398Z",
      "price": 0.88205,
      "previousClose": 0.88356,
      "dayHigh": 0.88205,
      "dayLow": 0.88205,
      "change": -0.0015100241,
      "changePercent": -0.17090227
    },
    {
      "timestamp": "2025-04-19T06:41:24.222Z",
      "price": 0.88205,
      "previousClose": 0.88356,
      "dayHigh": 0.88205,
      "dayLow": 0.88205,
      "change": -0.0015100241,
      "changePercent": -0.17090227
    },
    {
      "timestamp": "2025-04-19T06:41:40.598Z",
      "price": 0.88205,
      "previousClose": 0.88356,
      "dayHigh": 0.88205,
      "dayLow": 0.88205,
      "change": -0.0015100241,
      "changePercent": -0.17090227
    }
  ]
}