{
  "symbol": "GBPAUD=X",
  "history": [
    {
      "timestamp": "2025-04-19T06:40:49.627Z",
      "price": 2.08518,
      "previousClose": 2.07509,
      "dayHigh": 2.08518,
      "dayLow": 2.08518,
      "change": 0.010090113,
      "changePercent": 0.48624942
    },
    {
      "timestamp": "2025-04-19T06:41:02.485Z",
      "price": 2.08518,
      "previousClose": 2.07509,
      "dayHigh": 2.08518,
      "dayLow": 2.08518,
      "change": 0.010090113,
      "changePercent": 0.48624942
    },
    {
      "timestamp": "2025-04-19T06:41:15.887Z",
      "price": 2.08518,
      "previousClose": 2.07509,
      "dayHigh": 2.08518,
      "dayLow": 2.08518,
      "change": 0.010090113,
      "changePercent": 0.48624942
    },
    {
      "timestamp": "2025-04-19T06:41:29.999Z",
      "price": 2.08518,
      "previousClose": 2.07509,
      "dayHigh": 2.08518,
      "dayLow": 2.08518,
      "change": 0.010090113,
      "changePercent": 0.48624942
    }
  ]
}